factur_x_nolog-1.7.3.data/scripts/facturx-pdfextractxml
factur_x_nolog-1.7.3.data/scripts/facturx-pdfgen
factur_x_nolog-1.7.3.data/scripts/facturx-webservice
factur_x_nolog-1.7.3.data/scripts/facturx-xmlcheck
factur_x_nolog-1.7.3.dist-info/licenses/LICENSE
facturx/__init__.py
facturx/_version.py
facturx/facturx.py
facturx/xmp/Factur-X_extension_schema.xmp
facturx/xmp/ZUGFeRD_extension_schema.xmp
facturx/xsd/facturx-basic/Factur-X_1.07.2_BASIC.xsd
facturx/xsd/facturx-basic/Factur-X_1.07.2_BASIC_urn_un_unece_uncefact_data_standard_QualifiedDataType_100.xsd
facturx/xsd/facturx-basic/Factur-X_1.07.2_BASIC_urn_un_unece_uncefact_data_standard_ReusableAggregateBusinessInformationEntity_100.xsd
facturx/xsd/facturx-basic/Factur-X_1.07.2_BASIC_urn_un_unece_uncefact_data_standard_UnqualifiedDataType_100.xsd
facturx/xsd/facturx-basicwl/Factur-X_1.07.2_BASICWL.xsd
facturx/xsd/facturx-basicwl/Factur-X_1.07.2_BASICWL_urn_un_unece_uncefact_data_standard_QualifiedDataType_100.xsd
facturx/xsd/facturx-basicwl/Factur-X_1.07.2_BASICWL_urn_un_unece_uncefact_data_standard_ReusableAggregateBusinessInformationEntity_100.xsd
facturx/xsd/facturx-basicwl/Factur-X_1.07.2_BASICWL_urn_un_unece_uncefact_data_standard_UnqualifiedDataType_100.xsd
facturx/xsd/facturx-en16931/Factur-X_1.07.2_EN16931.xsd
facturx/xsd/facturx-en16931/Factur-X_1.07.2_EN16931_urn_un_unece_uncefact_data_standard_QualifiedDataType_100.xsd
facturx/xsd/facturx-en16931/Factur-X_1.07.2_EN16931_urn_un_unece_uncefact_data_standard_ReusableAggregateBusinessInformationEntity_100.xsd
facturx/xsd/facturx-en16931/Factur-X_1.07.2_EN16931_urn_un_unece_uncefact_data_standard_UnqualifiedDataType_100.xsd
facturx/xsd/facturx-extended/Factur-X_1.07.2_EXTENDED.xsd
facturx/xsd/facturx-extended/Factur-X_1.07.2_EXTENDED_urn_un_unece_uncefact_data_standard_QualifiedDataType_100.xsd
facturx/xsd/facturx-extended/Factur-X_1.07.2_EXTENDED_urn_un_unece_uncefact_data_standard_ReusableAggregateBusinessInformationEntity_100.xsd
factur_x_nolog-1.7.3.dist-info/METADATA
factur_x_nolog-1.7.3.dist-info/WHEEL
factur_x_nolog-1.7.3.dist-info/top_level.txt
factur_x_nolog-1.7.3.dist-info/RECORD
