Metadata-Version: 2.4
Name: factur-x-nolog
Version: 1.7.3
Summary: Factur-X and Order-X: electronic invoicing and ordering standards
Home-page: https://github.com/nathan30/factur-x
Author: Alexis de Lattre
Author-email: alexis.delattre@akretion.com
License: BSD
Keywords: e-invoice ZUGFeRD Factur-X Order-X e-procurement
Classifier: Development Status :: 5 - Production/Stable
Classifier: Intended Audience :: Developers
Classifier: Programming Language :: Python :: 2.7
Classifier: Programming Language :: Python :: 3.6
Classifier: Programming Language :: Python :: 3.7
Classifier: Programming Language :: Python :: 3.8
Classifier: Programming Language :: Python :: 3.9
Classifier: Programming Language :: Python :: 3.10
Classifier: License :: OSI Approved :: BSD License
Classifier: Operating System :: OS Independent
Classifier: Topic :: Office/Business :: Financial :: Accounting
License-File: LICENSE
Requires-Dist: pypdf
Requires-Dist: lxml
Dynamic: author
Dynamic: author-email
Dynamic: classifier
Dynamic: description
Dynamic: home-page
Dynamic: keywords
Dynamic: license
Dynamic: license-file
Dynamic: requires-dist
Dynamic: summary
